golem_base_sdk/__init__.py
golem_base_sdk/constants.py
golem_base_sdk/py.typed
golem_base_sdk/types.py
golem_base_sdk/utils.py
golem_base_sdk/wallet.py
golem_base_sdk-0.1.0.dist-info/licenses/LICENSE
golem_base_sdk-0.1.0.dist-info/WHEEL
golem_base_sdk-0.1.0.dist-info/METADATA
golem_base_sdk-0.1.0.dist-info/RECORD
