Metadata-Version: 2.4
Name: golem-base-sdk
Version: 0.1.0
Summary: GolemBase Python SDK.
Author-email: rvdp <online@well-founded.dev>
Requires-Python: >=3.10
License-Expression: GPL-3.0-only
License-File: LICENSE
Requires-Dist: anyio>=4.10.0
Requires-Dist: pyxdg>=0.28
Requires-Dist: rlp>=1.2.0
Requires-Dist: web3>=4.7.2
Project-URL: Documentation, https://golem-base.github.io/python-sdk/golem_base_sdk.html
Project-URL: Homepage, https://github.com/Golem-Base/
Project-URL: Issues, https://github.com/Golem-Base/python-sdk/issues
Project-URL: Repository, https://github.com/Golem-Base/python-sdk
